brook/__init__.py
brook/data.py
brook/models.py
brook/utils.py
brook-0.0.7.dist-info/LICENSE
brook-0.0.7.dist-info/METADATA
brook-0.0.7.dist-info/WHEEL
brook-0.0.7.dist-info/top_level.txt
brook-0.0.7.dist-info/RECORD
