Metadata-Version: 2.1
Name: brook
Version: 0.0.7
Summary: Custom python library
Home-page: https://gitlab.com/sh0416/brook
Author: Seonghyeon Lee
Author-email: seonghyeon.drew@gmail.com
License: UNKNOWN
Project-URL: Bug Reports, https://github.com/sh0416/brook/issues
Project-URL: Source, https://github.com/sh0416/brook/
Keywords: sample,setuptools,development
Platform: UNKNOWN
Classifier: Development Status :: 3 - Alpha
Classifier: Intended Audience :: Developers
Classifier: Topic :: Software Development :: Build Tools
Classifier: License :: OSI Approved :: MIT License
Classifier: Programming Language :: Python :: 3
Classifier: Programming Language :: Python :: 3.8
Classifier: Programming Language :: Python :: 3.9
Classifier: Programming Language :: Python :: 3 :: Only
Requires-Python: >=3.8, <4
Provides-Extra: dev
Requires-Dist: check-manifest ; extra == 'dev'
Provides-Extra: test
Requires-Dist: coverage ; extra == 'test'
